{"board": [["I", "C", "A", "R"], ["L", "T", "E", "T"], ["P", "A", "I", "S"], ["P", "S", "N", "O"]], "words": {"3": ["ONS", "OIS", "OSE", "NAP", "NAT", "NAE", "NAS", "NIE", "NIT", "NIS", "NOS", "SPA", "SAP", "SAL", "SAT", "SAE", "SAI", "SAN", "SIS", "SIT", "SIN", "SEC", "SEA", "SER", "SET", "SEI", "SON", "ITS", "ISO", "ION", "IOS", "INS", "APT", "APP", "ALT", "ALP", "AIT", "AIS", "AIN", "ANI", "ANS", "ASP", "PAP", "PAL", "PAT", "PAN", "PAS", "PSI", "EAN", "EAS", "EAR", "EAT", "ERA", "ETA", "EST", "TIC", "TIL", "TAR", "TAT", "TEC", "TEA", "TET", "TES", "TIE", "TIT", "TIS", "TIN", "TAP", "TAE", "TAI", "TAN", "TAS", "LIT", "LAP", "LAT", "LAS", "REC", "RET", "RES", "REI", "RAT", "ACE", "ACT", "ARE", "ART", "ATE", "ATS", "CIT", "CAR", "CAT", "ICE", "ITA"], "4": ["ONIE", "ONST", "NAPS", "NAES", "NIES", "NITE", "NITS", "NOSE", "SPAT", "SPAE", "SPAN", "SALT", "SALP", "SATE", "SATI", "SAIS", "SAIN", "SANS", "SIES", "SITS", "SIST", "PALP", "SNAP", "SNIT", "SIAL", "SITE", "SINS", "SEAL", "SEAN", "SEAS", "SECT", "SEAR", "SEAT", "SERA", "SETA", "SEIS", "STIE", "STET", "STAT", "STAR", "SONS", "ISNA", "IONS", "APPS", "ALIT", "ALPS", "AITS", "AINS", "ANIS", "PLAP", "PLAT", "PLAN", "PAPS", "PALI", "PATE", "PAIS", "PAIN", "PANS", "PSIS", "TITI", "TACT", "TRET", "TRES", "TRAT", "EANS", "ETIC", "ETAS", "EATS", "ETAT", "EINA", "TICE", "TACE", "TARE", "TART", "TATE", "TATS", "TEAL", "TEAS", "TEAR", "TEAT", "TETS", "TEST", "TEIN", "TIAN", "TIER", "TIES", "TITE", "TITS", "TINA", "TINS", "TAPS", "TALI", "TALC", "TAES", "TAIT", "TAIS", "TAIN", "TANS", "LICE", "LITE", "LAPS", "LATE", "LATI", "LAER", "LAIN", "REAP", "REAL", "REAN", "RETS", "REST", "REIS", "REIN", "RATA", "RACE", "RATE", "RATS", "ATAP", "ACER", "ACES", "ACTA", "AREA", "ARET", "ARES", "ARTI", "ARTS", "ATES", "CLIT", "CLAP", "CLAT", "CLAN", "CITE", "CARE", "CART", "CATE", "CATS", "CEAS", "CERT", "ICER", "ICES", "ITAS"], "5": ["ONSET", "OSIER", "OSTIA", "NATES", "NATIS", "NITER", "NITES", "NITRE", "NOISE", "NOSER", "SPLIT", "SPLAT", "SPALT", "SPATE", "SPAER", "SPAES", "SPAIT", "SPAIN", "SPANS", "SALIC", "SATES", "SATIS", "SATIN", "SAIST", "SAINS", "SITES", "SISTA", "SNIES", "SNITS", "PALPS", "SNAPS", "SISAL", "SITAR", "SEANS", "SETAL", "SERAC", "STEAL", "STEAN", "STEAR", "STEIN", "STATE", "STARE", "STRAE", "ISNAE", "INAPT", "INSET", "APTER", "APSIS", "ALTAR", "ALTER", "ANISE", "PLICA", "PLAPS", "PLATE", "PLAIT", "PLAIN", "PLANS", "PATER", "PATES", "PATIO", "PATIN", "PAISE", "PAINS", "PSION", "TITAN", "TECTA", "TACIT", "TREAT", "TRACE", "TRACT", "ETATS", "ECLAT", "TICES", "TACET", "TACES", "TARES", "TARTS", "TATIE", "TATER", "TATES", "TEATS", "TERTS", "TETRA", "TESTA", "TEINS", "TIANS", "TITER", "TITRE", "TINAS", "TAITS", "TAINS", "LITER", "LITES", "LITAI", "LITAS", "LATER", "REAPS", "REAIS", "REANS", "RECIT", "RECTI", "RECTA", "REATA", "REACT", "RETIA", "RESIT", "RESIN", "REIST", "REINS", "RATAL", "RATAN", "RATAS", "RACES", "RATIO", "RATES", "ATLAS", "ATAPS", "ACETA", "ACTIN", "AREAL", "AREAS", "ARETS", "ARTIS", "CLAPT", "CLAPS", "CLAES", "CLANS", "CLASP", "CITER", "CITES", "CITAL", "CARET", "CARES", "CARTE", "CARTS", "CATER", "CATES", "CERTS", "CESTI", "CESTA", "ICTAL"], "6": ["OSETRA", "OSTIAL", "OSTEAL", "NITRES", "NOSIER", "SPLICE", "SPATES", "SPAITS", "SPAINS", "SALTER", "SALTIE", "SATINS", "SANIES", "SANSEI", "SIESTA", "SISTER", "SISTRA", "SIALIC", "SEITAN", "STEALT", "STEANS", "STEINS", "STATIC", "STATER", "STATIN", "STATAL", "STACTE", "STRATI", "STRATA", "SONSIE", "SONATA", "ITALIC", "INSECT", "INSERT", "INSTAR", "APLITE", "APTEST", "PLICAE", "PLATER", "PLATES", "PLAITS", "PLAINS", "PTISAN", "PALTER", "PATERA", "PATIOS", "PATINS", "PANIER", "PSIONS", "TITANS", "TECTAL", "TERATA", "TRACES", "TATIES", "TATSOI", "TERTIA", "TESTIS", "TIETAC", "TITRES", "TANIST", "LITEST", "LATEST", "LATINO", "LANOSE", "RETAIN", "RECTAL", "REATAS", "RETIAL", "RETINA", "RESINS", "RATANS", "RATITE", "RATION", "RATIOS", "ACETAL", "ACETIN", "ACTION", "ACTINS", "ARTIES", "ARTSIE", "CLASPT", "CITIES", "CARETS", "CARTES", "CATION"], "7": ["OSTIATE", "NITRATE", "SPLICER", "SPLICES", "SALICET", "SALICES", "SALTCAT", "SALTATE", "SALTEST", "SALTIER", "SALTIES", "SECTION", "SEITANS", "STATICE", "STATION", "STATINS", "STRATAL", "STRATAS", "SONSIER", "INAPTER", "INSTATE", "APLITES", "AETATIS", "PLICATE", "PLATIER", "PLATIES", "PLAITER", "PTISANS", "PANSIES", "PSALTER", "TACTION", "ECTASIS", "TATSOIS", "TERTIAL", "TERTIAN", "TERTIAS", "TANSIES", "LATICES", "LATINOS", "RETAINS", "RECLASP", "RECITAL", "RECTION", "RETINAL", "RETINAS", "RETSINA", "RATITES", "RATIONS", "ACETINS", "ACTIONS", "ACTINAL", "ARTISAN", "ATRETIC", "ATRESIA", "CATIONS", "CERATIN"], "8": ["OSTINATI", "OSTEITIC", "NITRATES", "SALICETA", "SALICETS", "SALTCATS", "SALTATES", "SALTIEST", "SANITATE", "SECTIONS", "STEAPSIN", "STATIONS", "INAPTEST", "AERATION", "PLICATES", "PLATIEST", "PLAISTER", "TACTIONS", "TRACTION", "TERTIANS", "TIECLASP", "LITERATI", "LITANIES", "RECTIONS", "REACTION", "RETSINAS", "RESINATA", "RATANIES", "RATIONAL", "ARTISANS", "ARTESIAN", "ATRESIAS", "CITATION", "CERATINS"], "9": ["OSTRACEAN", "SALTATION", "SANITATES", "SECTIONAL", "STATIONAL", "APPLICATE", "AERATIONS", "PLICATION", "TRACTIONS", "REACTIONS", "RESTATION", "CITATIONS", "ITERATION"], "10": ["OSTRACEANS", "SALTATIONS", "ALTERATION", "PLICATIONS", "TRACTIONAL", "LITERATION", "RECITATION", "REACTIONAL", "RESTATIONS", "CITATIONAL", "ITERATIONS"], "11": ["APPLICATION", "ALTERATIONS", "LITERATIONS", "RECITATIONS"], "12": ["APPLICATIONS"], "13": ["REAPPLICATION"], "14": ["REAPPLICATIONS"], "15": []}}